khora/__init__.py
khora/__main__.py
khora/agents/__init__.py
khora/agents/data_fetcher.py
khora/agents/pipeline_builder.py
khora/pipelines/__init__.py
khora/pipelines/data_pipeline.py
khora/pipelines/definitions.py
khora/tools/__init__.py
khora/tools/api_tool.py
khora/tools/google_docs_tool.py
khora/tools/web_scraper_tool.py
khora/utils/__init__.py
khora/utils/config.py
khora/utils/data_models.py
khora-0.0.1.dist-info/METADATA
khora-0.0.1.dist-info/WHEEL
khora-0.0.1.dist-info/licenses/LICENSE
khora-0.0.1.dist-info/RECORD
