Metadata-Version: 2.4
Name: khora
Version: 0.0.1
Summary: Ad-hoc Dagster pipelines for data fetching using AI/LLM prompts and agentic AI
Project-URL: Homepage, https://github.com/yourusername/khora
Project-URL: Repository, https://github.com/yourusername/khora
Project-URL: Issues, https://github.com/yourusername/khora/issues
Author: Khora Team
License: MIT
License-File: LICENSE
Keywords: ai,dagster,data-fetching,langchain,langgraph,pipelines
Classifier: Development Status :: 3 - Alpha
Classifier: Intended Audience :: Developers
Classifier: License :: OSI Approved :: MIT License
Classifier: Programming Language :: Python :: 3
Classifier: Programming Language :: Python :: 3 :: Only
Classifier: Programming Language :: Python :: 3.12
Requires-Python: ==3.12.*
Requires-Dist: dagster-webserver>=1.7.0
Requires-Dist: dagster>=1.7.0
Requires-Dist: google-api-python-client>=2.120.0
Requires-Dist: google-auth-httplib2>=0.2.0
Requires-Dist: google-auth-oauthlib>=1.2.0
Requires-Dist: httpx>=0.27.0
Requires-Dist: langchain-community>=0.2.0
Requires-Dist: langchain-openai>=0.1.0
Requires-Dist: langchain>=0.2.0
Requires-Dist: langgraph>=0.1.0
Requires-Dist: pandas>=2.2.0
Requires-Dist: playwright>=1.45.0
Requires-Dist: pydantic>=2.7.0
Requires-Dist: python-dotenv>=1.0.0
Provides-Extra: dev
Requires-Dist: black>=24.4.0; extra == 'dev'
Requires-Dist: build>=1.2.0; extra == 'dev'
Requires-Dist: isort>=5.13.0; extra == 'dev'
Requires-Dist: mypy>=1.10.0; extra == 'dev'
Requires-Dist: pre-commit>=3.7.0; extra == 'dev'
Requires-Dist: pytest-asyncio>=0.23.0; extra == 'dev'
Requires-Dist: pytest-cov>=5.0.0; extra == 'dev'
Requires-Dist: pytest>=8.2.0; extra == 'dev'
Requires-Dist: ruff>=0.5.0; extra == 'dev'
Requires-Dist: twine>=5.1.0; extra == 'dev'
Requires-Dist: types-python-dateutil>=2.9.0; extra == 'dev'
Requires-Dist: types-pyyaml>=6.0.0; extra == 'dev'
Requires-Dist: types-requests>=2.32.0; extra == 'dev'
